{"id":"172338516139198_1216284815077891","from":{"name":"Amr Mohsen","id":"10212536669950599"},"message":"To Android Developers,\nI am building a project-lib with Maven that should export an aar so I can add it later to any of my projects at the dependencies, but at the final step when I try to run ./gradlew uploadArchives, it gives me this error which is seem to be an error finding the gradle version.\n\nAny idea how to solve this issue?","actions":[{"name":"Comment","link":"https://www.facebook.com/172338516139198/posts/1216284815077891"},{"name":"Like","link":"https://www.facebook.com/172338516139198/posts/1216284815077891"},{"name":"Report Post to Admin","link":"https://www.facebook.com/groups/egyptian.geeks/members/"}],"privacy":{"value":"","description":"","friends":"","allow":"","deny":""},"type":"status","created_time":"2016-08-28T01:28:18+0000","updated_time":"2016-08-28T01:44:03+0000","is_hidden":false,"is_expired":false,"likes":{"data":[{"id":"827049870776926","name":"Ahmed Mohamed Abd El-Hamid"}],"paging":{"cursors":{"before":"ODI3MDQ5ODcwNzc2OTI2","after":"ODI3MDQ5ODcwNzc2OTI2"}}},"comments":{"data":[{"created_time":"2016-08-28T01:28:57+0000","from":{"name":"Amr Mohsen","id":"10212536669950599"},"message":"I am depending on this tutorial: http://www.vandalsoftware.com/post/52468430435/publishing-an-android-library-aar-to-a-maven","can_remove":false,"like_count":0,"user_likes":false,"id":"1216285448411161"},{"created_time":"2016-08-28T01:43:58+0000","from":{"name":"Mohammed Hussien","id":"10154099730567024"},"message":"possibility of gradle versions duplicates or OS environment variables needs to be configured. not sure","can_remove":false,"like_count":0,"user_likes":false,"id":"1216293108410395"}],"paging":{"cursors":{"before":"WTI5dGJXVnVkRjlqZAFhKemIzSTZANVEl4TmpJNE5UUTBPRFF4TVRFMk1Ub3hORGN5TXpRM056TTQZD","after":"WTI5dGJXVnVkRjlqZAFhKemIzSTZANVEl4TmpJNU16RXdPRFF4TURNNU5Ub3hORGN5TXpRNE5qTTUZD"}}}}