{"id":"172338516139198_528650450508001","from":{"id":"100000116116716","name":"Mohamed Sameeh Sharaf"},"to":{"data":[{"name":"Egyptian Geeks","id":"172338516139198"}]},"message":":D","picture":"https://scontent-a.xx.fbcdn.net/hphotos-frc3/t1.0-9/s130x130/563028_505945932789531_1711444764_n.png","link":"https://www.facebook.com/Developers.egypt/photos/a.302602816457178.89920.176420202408774/505945932789531/?type=1","name":"Timeline Photos","properties":[{"name":"By","text":"مبرمجين مصر","href":"https://www.facebook.com/Developers.egypt?ref=stream"}],"icon":"https://fbstatic-a.akamaihd.net/rsrc.php/v2/yD/r/aS8ecmYRys0.gif","actions":[{"name":"Comment","link":"https://www.facebook.com/172338516139198/posts/528650450508001"},{"name":"Like","link":"https://www.facebook.com/172338516139198/posts/528650450508001"}],"privacy":{"value":""},"type":"photo","object_id":"505945932789531","created_time":"2013-02-11T18:21:04+0000","updated_time":"2013-02-11T23:38:39+0000","likes":{"data":[{"id":"100000224131120","name":"Moutaz Shams"},{"id":"1246823411","name":"Abdelrady Fcis"},{"id":"676490633","name":"Emad Mokhtar Habib"},{"id":"100000607202296","name":"Ahmed Hasan"}],"paging":{"cursors":{"after":"MTAwMDAwNjA3MjAyMjk2","before":"MTAwMDAwMjI0MTMxMTIw"}}},"comments":{"data":[{"id":"528755070497539","from":{"id":"1246823411","name":"Abdelrady Fcis"},"message":"mar7ab ostaz dardeery, eish a5barak :D =P","can_remove":false,"created_time":"2013-02-11T23:38:39+0000","like_count":0,"user_likes":false}],"paging":{"cursors":{"after":"NTI4NzU1MDcwNDk3NTM5","before":"NTI4NzU1MDcwNDk3NTM5"}}}}