{"id":"172338516139198_441758905863823","from":{"id":"100002045429029","name":"Mohamed Alaa El Din"},"to":{"data":[{"name":"Egyptian Geeks","id":"172338516139198"}]},"message":"Fedena is a free & opensource school management software that has more features than a student information system. Use fedena to efficiently manage students, teachers, employees, courses & all the system & process related to your institution.","caption":"Attachment UnavailableThis attachment may have been removed or the person who shared it may not have permission to share it with you.","actions":[{"name":"Comment","link":"https://www.facebook.com/172338516139198/posts/441758905863823"},{"name":"Like","link":"https://www.facebook.com/172338516139198/posts/441758905863823"}],"privacy":{"value":""},"type":"status","created_time":"2012-07-24T20:56:51+0000","updated_time":"2012-07-24T20:56:51+0000"}