{"id":"172338516139198_956092501097125","from":{"name":"Osama Soliman","id":"709206249239999"},"message":"You needn't worry about ur sensitive/important data again from bad/obtrusive  guys 3:) ... easily give 'em ur device/account after entering the fake password/pattern ... \n\nur account/device will have 2 passwords\n1st >> leads to real device with ur data\n2nd >> leads to fake device with fake date\n\n#Python small project Demo ... \nPlease who can co-operate with me developing this idea with native java for android ^_^ ? it's an easy one ... just a lock screen ... and hide files program .. mix together to get our project done","story":"Osama Soliman shared a link to the group: Egyptian Geeks.","story_tags":{"0":[{"id":"709206249239999","name":"Osama Soliman","type":"user","offset":0,"length":13}],"42":[{"id":"172338516139198","name":"Egyptian Geeks","type":"group","offset":42,"length":14}]},"picture":"https://fbexternal-a.akamaihd.net/safe_image.php?d=AQAVB0h17YzYEi_Y&w=130&h=130&url=https%3A%2F%2Favatars2.githubusercontent.com%2Fu%2F7149686%3Fv%3D3%26s%3D400&cfs=1&sx=0&sy=0&sw=400&sh=400&_nc_hash=AQD-WhNQ5gtNWwEv","link":"https://github.com/Microsmsm/SecondWayPassword","name":"Microsmsm/SecondWayPassword","caption":"github.com","description":"SecondWayPassword - This is small project .. a 2nd way password to protect u from bad guys by entering a fake password which will lead to fake date","icon":"https://www.facebook.com/images/icons/post.gif","actions":[{"name":"Comment","link":"https://www.facebook.com/172338516139198/posts/956092501097125"},{"name":"Like","link":"https://www.facebook.com/172338516139198/posts/956092501097125"},{"name":"Report Post to Admin","link":"https://www.facebook.com/groups/egyptian.geeks/members/"}],"privacy":{"value":"","description":"","friends":"","allow":"","deny":""},"type":"link","status_type":"shared_story","created_time":"2015-06-09T04:25:27+0000","updated_time":"2015-06-09T17:42:57+0000","is_hidden":false,"is_expired":false,"likes":{"data":[{"id":"1348336588561390","name":"Hosam Aly"},{"id":"10212106739285334","name":"Muhammad Sabry Abdulwanis"},{"id":"1615887465092802","name":"Abdelrahman M. Moez"},{"id":"770108719813462","name":"Ali Zawahry"},{"id":"1253681964729491","name":"Eslam Esmaeal"},{"id":"1879545615654647","name":"Ziad Mohamed Khobeiz"},{"id":"1190206551076596","name":"Mohamed Wael"},{"id":"1015999261865497","name":"Muhammad Tarek"},{"id":"10211111455435727","name":"Mohamed Shaban"},{"id":"1664976033803696","name":"Ahmed Jadelrab"}],"paging":{"cursors":{"before":"MTM0ODMzNjU4ODU2MTM5MAZDZD","after":"MTY2NDk3NjAzMzgwMzY5NgZDZD"}}},"comments":{"data":[{"created_time":"2015-06-09T04:29:11+0000","from":{"name":"Ahmed Saleh","id":"1384434324953403"},"message":"Fake account. Lol :D that's a lot to hide.","can_remove":false,"like_count":0,"user_likes":false,"id":"956093201097055"},{"created_time":"2015-06-09T04:31:35+0000","from":{"name":"Osama Soliman","id":"709206249239999"},"message":"yea 3:) enough to be jailed the next 10 years xD ! -hv u read the code :D ?-","can_remove":false,"like_count":1,"user_likes":false,"id":"956093494430359"},{"created_time":"2015-06-09T04:33:50+0000","from":{"name":"Ahmed Saleh","id":"1384434324953403"},"message":"u can rather create fake files and encrypt data them than doing another password.","can_remove":false,"like_count":0,"user_likes":false,"id":"956094831096892"},{"created_time":"2015-06-09T04:35:30+0000","from":{"name":"Osama Soliman","id":"709206249239999"},"message":"it's an easy option when u have pattern in ur hand ... and in a tight situation ... just go along with the fake password/pattren","can_remove":false,"like_count":0,"user_likes":false,"id":"956095887763453"},{"created_time":"2015-06-09T04:37:49+0000","from":{"name":"Osama Soliman","id":"709206249239999"},"message":"or i didn't got what u said Ahmed ?","can_remove":false,"like_count":0,"message_tags":[{"id":"1384434324953403","length":5,"name":"Ahmed Saleh","offset":28,"type":"user"}],"user_likes":false,"id":"956096664430042"},{"created_time":"2015-06-09T04:39:09+0000","from":{"name":"Ahmed Saleh","id":"1384434324953403"},"message":"It's cool, but encrypting the data is better. never the less, we shouldn't have to encrypt anything and live free in your country unless you are creating criminal thing.","can_remove":false,"like_count":0,"user_likes":false,"id":"956097944429914"},{"created_time":"2015-06-09T04:48:25+0000","from":{"name":"Osama Soliman","id":"709206249239999"},"message":"I don't want to talk about politics here it's a Raw programming topic .. but I hv sent u an Inbox ^_^","can_remove":false,"like_count":1,"user_likes":false,"id":"956101781096197"},{"created_time":"2015-06-09T05:39:23+0000","from":{"name":"Ahmed Jadelrab","id":"1664976033803696"},"message":"Smart idea, Good luck, I would love to see it soon as Android App.","can_remove":false,"like_count":1,"user_likes":false,"id":"956117254427983"},{"created_time":"2015-06-09T08:02:36+0000","from":{"name":"Essam A. Hassan","id":"1246324408754353"},"message":"I like the idea very much :D I got similar feature on my LG G3 phone :D another password will result in guest environment where I choose backgrounds and specific content to show including apps and assets \neven settings can be restricted","can_remove":false,"like_count":2,"user_likes":false,"id":"956192094420499"},{"created_time":"2015-06-09T12:35:43+0000","from":{"name":"Osama Soliman","id":"709206249239999"},"message":"Ahmed Abdelrahim thx :) \nEssam A. Hassan can u check ur mobile and tell me the name of the feature so I can search it, please ^_^ ? ... \n\nplease if u can help me rewrite the description of this project or have name suggestions ... I will be very happy to hear it <3 \nunfortunately ... u know :D computer only understand coders xD !","can_remove":false,"like_count":1,"message_tags":[{"id":"1664976033803696","length":16,"name":"Ahmed Jadelrab","offset":0,"type":"user"},{"id":"1246324408754353","length":15,"name":"Essam A. Hassan","offset":25,"type":"user"}],"user_likes":false,"id":"956262227746819"},{"created_time":"2015-06-09T14:58:14+0000","from":{"name":"Osama Soliman","id":"709206249239999"},"message":"seems someone solved that problem before me :) ! on LG devices .. \nAnyway I liked that I tried to do something ... \nhttps://www.youtube.com/watch?v=Mxy7VpIWTRU","can_remove":false,"like_count":0,"user_likes":false,"id":"956305171075858"},{"created_time":"2015-06-09T17:31:36+0000","from":{"name":"Ali Zawahry","id":"770108719813462"},"message":"This was done on Truecrypt although on a low hard disk encryption level.","can_remove":false,"like_count":0,"user_likes":false,"id":"956346437738398"},{"created_time":"2015-06-09T17:42:57+0000","from":{"name":"Abdelrahman M. Moez","id":"1615887465092802"},"message":"I think to deceive attacker with fake data is better than telling him data is encrypted break it :D \nOr ...  both, encrypting original data and misleading to fake data is much better! :v","can_remove":false,"like_count":1,"user_likes":false,"id":"956349451071430"}],"paging":{"cursors":{"before":"WTI5dGJXVnVkRjlqZAFhKemIzSTZAPVFUyTURrek1qQXhNRGszTURVMU9qRTBNek00TWpReE5URT0ZD","after":"WTI5dGJXVnVkRjlqZAFhKemIzSTZAPVFUyTXpRNU5EVXhNRGN4TkRNd09qRTBNek00TnpFM056Yz0ZD"}}}}