{"id":"172338516139198_1141800725859634","from":{"name":"Mohamed A. Alqrwash","id":"10210601405564635"},"message":"Hi GeeKs ,  i would like to ask where could i get \" Axiom m5235BCC Coldfire Evaluation board \"\nin Egypt and { if else } could i run RTEMS 4.10 Operating System \nin arduino or  raspberry pi","actions":[{"name":"Comment","link":"https://www.facebook.com/172338516139198/posts/1141800725859634"},{"name":"Like","link":"https://www.facebook.com/172338516139198/posts/1141800725859634"},{"name":"Report Post to Admin","link":"https://www.facebook.com/groups/egyptian.geeks/members/"}],"privacy":{"value":"","description":"","friends":"","allow":"","deny":""},"type":"status","created_time":"2016-05-11T22:17:12+0000","updated_time":"2016-05-12T13:41:11+0000","is_hidden":false,"is_expired":false,"comments":{"data":[{"created_time":"2016-05-12T01:12:54+0000","from":{"name":"Ahmad Alfy","id":"10154097389365670"},"message":"It's hard to keep up with all these new pokemons ...","can_remove":false,"like_count":1,"user_likes":false,"id":"1141871312519242"},{"created_time":"2016-05-12T13:05:19+0000","from":{"name":"Mohamed A. Alqrwash","id":"10210601405564635"},"message":"i know","can_remove":false,"like_count":1,"user_likes":false,"id":"1142109392495434"},{"created_time":"2016-05-12T13:07:27+0000","from":{"name":"Mohamed A. Alqrwash","id":"10210601405564635"},"message":"i try to test abstract layer operating system","can_remove":false,"like_count":0,"user_likes":false,"id":"1142113565828350"},{"created_time":"2016-05-12T13:09:21+0000","from":{"name":"Ahmad Alfy","id":"10154097389365670"},"message":"Mahmoud Tantawy You're the raspberry pii master I know ....","can_remove":false,"like_count":0,"message_tags":[{"id":"10155099548114764","length":15,"name":"Mahmoud Tantawy","offset":0,"type":"user"}],"user_likes":false,"id":"1142115099161530"},{"created_time":"2016-05-12T13:30:40+0000","from":{"name":"Mahmoud Tantawy","id":"10155099548114764"},"message":"I haven't used the board you mentioned before but you are most likely to find that board -if it is being sold in Egypt- by checking where the likes of Raspberry Pi and Arduino are being sold in Egypt, this can be done by googling \"raspberry pi Egypt\" and/or \"Arduno Egypt\"","can_remove":false,"like_count":1,"user_likes":false,"id":"1142133679159672"},{"created_time":"2016-05-12T13:31:43+0000","from":{"name":"Mahmoud Tantawy","id":"10155099548114764"},"message":"Concerning the RTOS, i haven't seen an official thingy being developed -and maintained- for RPi or Arduino, however, some googling reveal some attempts at porting and old personal projects, nothing shiny though","can_remove":false,"like_count":1,"user_likes":false,"id":"1142133945826312"},{"created_time":"2016-05-12T13:31:48+0000","from":{"name":"Mahmoud Tantawy","id":"10155099548114764"},"message":"Check http://alanstechnotes.blogspot.com.eg/2013/03/rtems-on-raspberry-pi.html","can_remove":false,"like_count":1,"user_likes":false,"id":"1142133965826310"},{"created_time":"2016-05-12T13:31:53+0000","from":{"name":"Mahmoud Tantawy","id":"10155099548114764"},"message":"And http://forum.arduino.cc/index.php?topic=138643.0","can_remove":false,"like_count":1,"user_likes":false,"id":"1142134035826303"},{"created_time":"2016-05-12T13:32:25+0000","from":{"name":"Mohamed A. Alqrwash","id":"10210601405564635"},"message":"thanks :: that's it :-)","can_remove":false,"like_count":1,"user_likes":false,"id":"1142134209159619"},{"created_time":"2016-05-12T13:38:24+0000","from":{"name":"Ahmad Alfy","id":"10154097389365670"},"message":"","can_remove":false,"like_count":3,"user_likes":false,"id":"1142136715826035"},{"created_time":"2016-05-12T13:41:11+0000","from":{"name":"Mohamed A. Alqrwash","id":"10210601405564635"},"message":"thank's Ahmad Alfy , i will try Trying out RTEMS on the Raspberry Pi\nand i hope to get it work :-)","can_remove":false,"like_count":1,"message_tags":[{"id":"10154097389365670","length":10,"name":"Ahmad Alfy","offset":8,"type":"user"}],"user_likes":false,"id":"1142138649159175"}],"paging":{"cursors":{"before":"WTI5dGJXVnVkRjlqZAFhKemIzSTZANVEUwTVRnM01UTXhNalV4T1RJME1qb3hORFl6TURFMU5UYzAZD","after":"WTI5dGJXVnVkRjlqZAFhKemIzSTZANVEUwTWpFek9EWTBPVEUxT1RFM05Ub3hORFl6TURZAd05EY3gZD"}}}}