{"id":"172338516139198_1223159887723717","from":{"name":"سامح دعبس","id":"1873036762957490"},"actions":[{"name":"Comment","link":"https://www.facebook.com/172338516139198/posts/1223159887723717"},{"name":"Like","link":"https://www.facebook.com/172338516139198/posts/1223159887723717"},{"name":"Report Post to Admin","link":"https://www.facebook.com/groups/egyptian.geeks/members/"}],"privacy":{"value":"","description":"","friends":"","allow":"","deny":""},"type":"status","created_time":"2016-09-04T21:09:23+0000","updated_time":"2016-09-05T17:49:05+0000","shares":{"count":1},"is_hidden":false,"is_expired":false,"likes":{"data":[{"id":"10210954655734032","name":"Amjad Mashaal"},{"id":"10155075474711294","name":"Ali Salem Korayem"},{"id":"1118459391596579","name":"Mohamad Emad"},{"id":"1354622807933087","name":"Nader Nabil"},{"id":"1285105998248677","name":"Ahmed Badawy"},{"id":"1323788571020648","name":"Ibrahim Shoaib"},{"id":"10212587285024102","name":"Mostafa Closed"}],"paging":{"cursors":{"before":"MTAyMTA5NTQ2NTU3MzQwMzIZD","after":"MTAyMTI1ODcyODUwMjQxMDIZD"}}},"comments":{"data":[{"created_time":"2016-09-04T23:00:28+0000","from":{"name":"Meligy","id":"10154884040385170"},"message":"Anybody knows this guy? A whole lot of very big yet unsupported claims","can_remove":false,"like_count":4,"user_likes":false,"id":"1223226707717035"},{"created_time":"2016-09-04T23:06:58+0000","from":{"name":"سامح دعبس","id":"1873036762957490"},"message":"أحمد سلام تقدر تعتبره من مؤسسي صخر (في أيامها الخوالي) لما كانوا يعملوا اختراعات في صناعة البرمجات بجد","can_remove":false,"like_count":0,"user_likes":false,"id":"1223233897716316"},{"created_time":"2016-09-04T23:09:09+0000","from":{"name":"سامح دعبس","id":"1873036762957490"},"message":"https://www.linkedin.com/in/ahmedsallam","can_remove":false,"like_count":2,"user_likes":false,"id":"1223234951049544"},{"created_time":"2016-09-04T23:09:59+0000","from":{"name":"Amir Abou Eesa","id":"1353018234756623"},"message":"حسيت نفس الاحساس من الكلام\n\"الاداه المصنفه الاولى علي العالم في كشف الفيروسات الخفيه، الجمله دي مش جمله حد بالحجم ده !\" الموبيل الي متصمم لجون كيري ولو بعد عنه بيعمل مش عارف ايه ، انا معلوماتي في السيكيوريتي مش اوي بس الكلام صيغته غريبه","can_remove":false,"like_count":1,"user_likes":false,"id":"1223235307716175"},{"created_time":"2016-09-04T23:15:59+0000","from":{"name":"سامح دعبس","id":"1873036762957490"},"message":"ادخلوا على صفحته على لينكد إن, انزلوا تحت شوية على براءات الاختراع (الكتير قوي), شوف اللي فيهم مرتبط بالسيكيوريتي, و دوس على اللينكات بتاعتها.\nملاحظة, الراجل كان كاتب ذكريات كتيرة على صفحته \"العامة\" مش الفنية على الفيسبوك عن تجربته في ضخر - وغيرها-\nراجل برنس ف نفسه الصراحة, خلينا نتعلم منه أي حاجة!","can_remove":false,"like_count":0,"user_likes":false,"id":"1223238031049236"},{"created_time":"2016-09-04T23:17:27+0000","from":{"name":"Zeyad Kenawi","id":"1865899380356786"},"message":"هههه حسيت اني هلاقي البوست متوقع ب نبيل فاروق","can_remove":false,"like_count":1,"user_likes":false,"id":"1223240264382346"},{"created_time":"2016-09-04T23:23:19+0000","from":{"name":"Amir Abou Eesa","id":"1353018234756623"},"message":"مع احترامي للشخص ولاننا المفروض نتعلم بس الكلام كله مش منطقي \nميطلعش من حد تقني\nهو ايه التحكم في الحدود الجغرافيه ده \nغير موضوع تراخيص الانتي فيرس \nغير الموبيل نفسه الي بيتكلم عنه\nالهاكر والفيروس ، معتقدش ان حد بالبروفيل ده هيخطا في المسميات\nحاجات كتير اوي تشككنا ومحتاجه شرح وتوضيح عشان نتعلم","can_remove":false,"like_count":3,"user_likes":false,"id":"1223243687715337"},{"created_time":"2016-09-04T23:58:31+0000","from":{"name":"عز وحيد","id":"10212583122712594"},"message":"بصراحة ومع احترامى ليه انا كل الى أحب افهمه فى البوست ده هو الكمتين دول :\nذكرني هذا أثناء عملي السابق في مضادات الفيروسات حين إكتشفنا مصادفة فيروسات مختفية على بعض الحاسبات والتي تبين أنها كانت لإستعمال الرئيس مبارك وعائلته بقصر القبة.","can_remove":false,"like_count":0,"user_likes":false,"id":"1223266957713010"},{"created_time":"2016-09-05T02:45:12+0000","from":{"name":"Anwer Matter","id":"10158408864315444"},"message":"انا اشتغلت هنا في صخر عمان مع ناس تقدر تقول اشتغلوا معاه .....\nالراجل اسس اهم منتجات صخر في بداياتها كان ايامها حازم عبد العظيم هو مدير الشركة","can_remove":false,"like_count":0,"user_likes":false,"id":"1223362724370100"},{"created_time":"2016-09-05T08:11:47+0000","from":{"name":"Ashraf Kaabi","id":"10155206502385921"},"message":"البوست كل جملة فيها ملهاش علاقة باللى قبليها غير انه مسلط الضوء على ازاي انه جامد اوي و ان الحكومة و الشركات في مصر مش مقدرة حجمه فى مجال الحماية !","can_remove":false,"like_count":0,"user_likes":false,"id":"1223536311019408"},{"created_time":"2016-09-05T11:08:12+0000","from":{"name":"Mohamed Fergany","id":"10212218310718439"},"message":"هو الواضح انه كان ماسك السيكورتي في انتل ومسك السيكورتي في اكتر من مكان منهم سيمنتك","can_remove":false,"like_count":0,"user_likes":false,"id":"1223635267676179"},{"created_time":"2016-09-05T11:14:57+0000","from":{"name":"Meligy","id":"10154884040385170"},"message":"هو الكلام أوفر بس صفحة الـ LinkedIn إلى حد كبير بتقول إنه ممكن يكون جامد التنين زي ما بيقول.\nأكتر حاجة شككتني فيه القفلة بتاعة Smart Dust دي. حستها اشتغالة ومادورتش حتى. خطأ كبير من ناحيتي. مش عارف مدى الكلام في العالم الواقعي إيه، بس على الأقل الدخان ليه ولو شرارة نابع منها مش من نسج خيال الكاتب\nhttp://singularityhub.com/2016/06/28/smart-dust-is-coming-new-camera-is-the-size-of-a-grain-of-salt/","can_remove":false,"like_count":3,"user_likes":false,"id":"1223638097675896"},{"created_time":"2016-09-05T11:30:48+0000","from":{"name":"Anwer Matter","id":"10158408864315444"},"message":"من ناحية جامد التنين ... فهو فعلا جامد ودي معلومة انا متأكد منها\nالراجل اشتغل على تطبيقات قوية جدا وهو من مؤسسينها فعلا ...\n تطبيقات زي متصفح آمن في التسعينات كانت مجرد خيال أيامها\nصخر كانت سابقا عصرها وفيها كنوز فعلا\nنظام تشغيل عربي (مبني ع الويندوز ) .... متصفح  .... محرك بحث بيبحث في حاجة زي ملفات او قواعد بيانات .... تحويل نص لصوت وصوت لنص ... ترجمه .... OCR\nكل ده في التسعينات .... الله يرحمها شركة بقى ...\n\nطبعا ممكن يكون بيبالغ ماقلتش لأ ... بس الراجل جامد وقديم ... دي حقيقة فعلا","can_remove":false,"like_count":2,"user_likes":false,"id":"1223646027675103"},{"created_time":"2016-09-05T17:49:03+0000","from":{"name":"سامح دعبس","id":"1873036762957490"},"message":"هو الحقيقة لأني عارف الراجل و موهوم بيه (هو جامد تنين فعلا) فربما ما ركزتش في الكلام اللي هو قايله قوي, لعل ده اللي بيسموه تأثير الهالة. خطأ مني طبعا.\nلما لقيت الناس - اللي مش عارفاه - بتنتقده فركزت و أعدت قراءة الكلام تاني, لقيت مفهوش حاجة غريبة عليا إلا الsmart dust دي اللي حسيت ممكن يكون فيها أفورة. بس لما بحثت عنها لقيت إنها موجودة بالفعل بس احنا اللي مش عارفين.\nشكرا على نشر الروح النقدية :*","can_remove":false,"like_count":1,"user_likes":false,"id":"1223895164316856"}],"paging":{"cursors":{"before":"WTI5dGJXVnVkRjlqZAFhKemIzSTZANVEl5TXpJeU5qY3dOemN4TnpBek5Ub3hORGN6TURNd01ESTQZD","after":"WTI5dGJXVnVkRjlqZAFhKemIzSTZANVEl5TXpnNU5URTJORE14TmpnMU5qb3hORGN6TURrM056UXoZD"}}}}