{"id":"172338516139198_784558121583898","from":{"id":"695596001","name":"Muhammad Saleh"},"to":{"data":[{"name":"Egyptian Geeks","id":"172338516139198"}]},"message":"I've always admired the old UI for Airbnb and now they redesigned the whole website\nThe old one wasn't responsive, unfortunately this one isn't responsive too","caption":"Attachment UnavailableThis attachment may have been removed or the person who shared it may not have permission to share it with you.","actions":[{"name":"Comment","link":"https://www.facebook.com/172338516139198/posts/784558121583898"},{"name":"Like","link":"https://www.facebook.com/172338516139198/posts/784558121583898"}],"privacy":{"value":""},"type":"status","created_time":"2014-07-16T19:15:46+0000","updated_time":"2014-07-17T09:25:15+0000","likes":{"data":[{"id":"597496183","name":"Ahmed Salem"}],"paging":{"cursors":{"after":"NTk3NDk2MTgz","before":"NTk3NDk2MTgz"}}},"comments":{"data":[{"id":"784579841581726","from":{"id":"100002045429029","name":"Mohamed Alaa El Din"},"message":"I admire the map view! i don't understand why Real Estate companies are so behind on this!","can_remove":true,"created_time":"2014-07-16T20:21:50+0000","like_count":1,"user_likes":false},{"id":"784809548225422","from":{"id":"695596001","name":"Muhammad Saleh"},"message":"I thought that when Airbnb revamps their website it will be something amazing.. it's not that bad but still not responsive","can_remove":true,"created_time":"2014-07-17T09:25:15+0000","like_count":0,"user_likes":false}],"paging":{"cursors":{"after":"WTI5dGJXVnVkRjlqZFhKemIzSTZOemcwT0RBNU5UUTRNakkxTkRJeU9qRTBNRFUxT0RreE1UVTZMVEU9","before":"WTI5dGJXVnVkRjlqZFhKemIzSTZOemcwTlRjNU9EUXhOVGd4TnpJMk9qRTBNRFUxTkRJeE1UQTZMVEU9"}}}}