{"id":"172338516139198_1337996242906747","from":{"name":"Mohammed Salah ElDin Mohammed","id":"10155107982908410"},"message":"Hi guys, \n\nThe GM asked me to find a way for a rapid development cross platform system.. He wants to increase the productivity but I have concerns regarding the ready made tools rather I want a tool that can generate cross platform code but give me the ability to customize the code and add an architectural touch on it. \n\nCould you help please?","actions":[{"name":"Comment","link":"https://www.facebook.com/172338516139198/posts/1337996242906747"},{"name":"Like","link":"https://www.facebook.com/172338516139198/posts/1337996242906747"},{"name":"Report Post to Admin","link":"https://www.facebook.com/groups/egyptian.geeks/members/"}],"privacy":{"value":"","description":"","friends":"","allow":"","deny":""},"type":"status","created_time":"2016-12-26T14:16:37+0000","updated_time":"2016-12-28T20:30:37+0000","is_hidden":false,"is_expired":false,"comments":{"data":[{"created_time":"2016-12-26T14:55:51+0000","from":{"name":"Ahmed Al-Amir","id":"10155179919799180"},"message":"There are no silver bullets. Even the choice to go crossplatform vs native depends on what you are doing and how you want to achieve it. Generic requests like \"increased productivity\" are usually a sign of bad things to come. What exactly is your GM trying to achieve?","can_remove":false,"like_count":3,"user_likes":false,"id":"1338030149570023"},{"created_time":"2016-12-27T13:59:45+0000","from":{"name":"Amr ELsaqqa","id":"10155181258139701"},"message":"Cross platform for what? Desktop, mobile?","can_remove":false,"like_count":0,"user_likes":false,"id":"1338814979491540"},{"created_time":"2016-12-28T20:30:35+0000","from":{"name":"Hossam Saraya","id":"10158512210325389"},"message":"I would go with React, React Native & Electron","can_remove":false,"like_count":3,"user_likes":false,"id":"1339834082722963"}],"paging":{"cursors":{"before":"WTI5dGJXVnVkRjlqZAFhKemIzSTZANVE16T0RBek1ERTBPVFUzTURBeU16b3hORGd5TnpZAME1UVXgZD","after":"WTI5dGJXVnVkRjlqZAFhKemIzSTZANVE16T1Rnek5EQTRNamN5TWprMk16b3hORGd5T1RVM01ETTEZD"}}}}