{"id":"172338516139198_772985602741150","from":{"id":"100003473671632","name":"مروان عبد المنعم"},"to":{"data":[{"name":"Egyptian Geeks","id":"172338516139198"}]},"message":"i know how the data are exist in memory,\nbut what is a program, lets say a service/process works as a server to serve web requests\nwhat is this service in the system? i mean at the level of memory/processor?\nwhere it lives?","actions":[{"name":"Comment","link":"https://www.facebook.com/172338516139198/posts/772985602741150"},{"name":"Like","link":"https://www.facebook.com/172338516139198/posts/772985602741150"}],"privacy":{"value":""},"type":"status","created_time":"2014-06-29T14:27:45+0000","updated_time":"2014-06-29T16:42:16+0000","comments":{"data":[{"id":"773008029405574","from":{"id":"1450696138","name":"Saif Al-Dein M. Helmy"},"message":"The program itself is treated as data, it is stored in memory and the processor knows which instruction is being processed now (it's address) and once it is executed the CPU fetches the next one in memory (or the instruction itself is a jump instruction, which tells the processor that the next instruction is located at another location in memory and not just the next instruction in memory after this one)\n\nPS : That is just a simple abstraction","can_remove":false,"created_time":"2014-06-29T14:56:45+0000","like_count":1,"user_likes":false},{"id":"773055486067495","from":{"id":"100003473671632","name":"مروان عبد المنعم"},"message":"mmm start to understand, thanks for the info","can_remove":false,"created_time":"2014-06-29T16:42:16+0000","like_count":0,"user_likes":false}],"paging":{"cursors":{"after":"NzczMDU1NDg2MDY3NDk1","before":"NzczMDA4MDI5NDA1NTc0"}}}}