{"id":"172338516139198_653177944721917","from":{"id":"100002623936802","name":"Ahmed PiTech"},"to":{"data":[{"name":"Egyptian Geeks","id":"172338516139198"}]},"message":"Visit Us to Get 10% discount about all training services during November","picture":"https://fbcdn-sphotos-d-a.akamaihd.net/hphotos-ak-xpf1/v/t1.0-9/s130x130/1459271_507225996041527_819840431_n.jpg?oh=ff03fc2ba8b4ce696303a46a43c910bd&oe=54B9550F&__gda__=1425534435_99cf0b99361afbd099998357ee325fc0","link":"https://www.facebook.com/photo.php?fbid=507225996041527&set=gm.653177944721917&type=1&relevant_count=1","icon":"https://fbstatic-a.akamaihd.net/rsrc.php/v2/yz/r/StEh3RhPvjk.gif","actions":[{"name":"Comment","link":"https://www.facebook.com/172338516139198/posts/653177944721917"},{"name":"Like","link":"https://www.facebook.com/172338516139198/posts/653177944721917"}],"privacy":{"value":""},"type":"photo","object_id":"507225996041527","created_time":"2013-11-14T07:23:39+0000","updated_time":"2013-11-14T07:23:39+0000"}