{"id":"172338516139198_525182780854768","from":{"id":"100002045429029","name":"مُحَمَّد أبو آدم"},"to":{"data":[{"name":"Egyptian Geeks","id":"172338516139198"}]},"message":"If you have a FB app make sure you start migrating to February updates.","caption":"Attachment UnavailableThis attachment may have been removed or the person who shared it may not have permission to share it with you.","actions":[{"name":"Comment","link":"https://www.facebook.com/172338516139198/posts/525182780854768"},{"name":"Like","link":"https://www.facebook.com/172338516139198/posts/525182780854768"}],"privacy":{"value":""},"type":"status","created_time":"2013-02-04T07:16:18+0000","updated_time":"2013-02-04T07:16:18+0000"}