{"id":"172338516139198_817366251636418","from":{"id":"544815169","name":"Mohamed Meligy"},"to":{"data":[{"name":"EgyptianGeeksJobs","id":"673428112750757"},{"name":"Egyptian Geeks","id":"172338516139198"}]},"message":"Jobs go to EgyptianGeeksJobs.\n\nJob ads posted here will be deleted, often without warning.","message_tags":{"11":[{"id":"673428112750757","name":"EgyptianGeeksJobs","type":"group","offset":11,"length":17}]},"actions":[{"name":"Comment","link":"https://www.facebook.com/172338516139198/posts/817366251636418"},{"name":"Like","link":"https://www.facebook.com/172338516139198/posts/817366251636418"}],"privacy":{"value":""},"type":"status","created_time":"2014-09-21T00:49:16+0000","updated_time":"2014-09-22T20:26:14+0000","likes":{"data":[{"id":"755026046","name":"Mosab Ahmad"},{"id":"595125669","name":"Ahmad Alfy"},{"id":"695596001","name":"Muhammad Saleh"},{"id":"100002045429029","name":"Mohamed Alaa El Din"}],"paging":{"cursors":{"after":"MTAwMDAyMDQ1NDI5MDI5","before":"NzU1MDI2MDQ2"}}},"comments":{"data":[{"id":"817480191625024","from":{"id":"753204477","name":"Khaled Ramadan"},"message":"You should send warning before deleting it because in one of group admin's status before he said job post \"ACCEPTED\" here, so if you changed your policy then you should send warning or at least post a new status concerning your new policy","can_remove":true,"created_time":"2014-09-21T08:20:31+0000","like_count":0,"user_likes":false},{"id":"817547324951644","from":{"id":"1055914266","name":"Hady Ahmad"},"message":"Khaled Ramadan Not really, no. This new policy has been in effect for sometime now and we've been sending out warnings to quite a few of these misplaced job ads. The policy is clear, do read it.\n\nThe admin status you're referring to was in fact a really old poll and the new policy has been discussed previously, in two pinned statuses one of which was an announcement.","message_tags":[{"id":"753204477","name":"Khaled Ramadan","type":"user","offset":0,"length":14}],"can_remove":true,"created_time":"2014-09-21T12:25:43+0000","like_count":2,"user_likes":false},{"id":"817602538279456","from":{"id":"544815169","name":"Mohamed Meligy"},"message":"The new group has been there since July 11. The new group was made specifically to move posts from here. Any member old enough to see discussions before that is expected to have seen this too and a few warned job posts. It's new members that find it hard to comply. I do not blame them for not reading group description well, it's not common to do so in facebook groups.","can_remove":true,"created_time":"2014-09-21T14:51:56+0000","like_count":1,"user_likes":false},{"id":"817863708253339","from":{"id":"652024918","name":"Amr Eldib"},"message":"If I add a comment to a post, then delete the post. Does the post author still get to see my comment?","can_remove":true,"created_time":"2014-09-22T03:49:32+0000","like_count":0,"user_likes":false},{"id":"817889838250726","from":{"id":"544815169","name":"Mohamed Meligy"},"message":"They might. If they have email notification on comments, and if facebook sent the email before the post was deleted (a big IF), and if they read those notifications (don't get buried by Gmail, categories, etc.)","can_remove":true,"created_time":"2014-09-22T05:31:29+0000","like_count":1,"user_likes":true},{"id":"817890214917355","from":{"id":"544815169","name":"Mohamed Meligy"},"message":"So, quite unlikely, although *might* be possible.","can_remove":true,"created_time":"2014-09-22T05:33:41+0000","like_count":1,"user_likes":false},{"id":"818148548224855","from":{"id":"587461065","name":"Shady M. Najib"},"message":"I guess making Meligy's post (this very post, above) a sticky one is enough as warning :)","message_tags":[{"id":"544815169","name":"Meligy","type":"user","offset":15,"length":6}],"can_remove":true,"created_time":"2014-09-22T20:26:14+0000","like_count":1,"user_likes":false}],"paging":{"cursors":{"after":"WTI5dGJXVnVkRjlqZFhKemIzSTZPREU0TVRRNE5UUTRNakkwT0RVMU9qRTBNVEUwTVRjMU56UTZMVEU9","before":"WTI5dGJXVnVkRjlqZFhKemIzSTZPREUzTkRnd01Ua3hOakkxTURJME9qRTBNVEV5T0RjMk16RTZMVEU9"}}}}