{"id":"172338516139198_829026050470438","from":{"id":"544815169","name":"Mohamed Meligy"},"to":{"data":[{"name":"Egyptian Geeks","id":"172338516139198"}]},"message":"English version of YouTube production video is also here:\nhttps://www.youtube.com/playlist?list=PLpjK416fmKwSTDO-d8-6Zod-aC-8e-jq5","caption":"Attachment UnavailableThis attachment may have been removed or the person who shared it may not have permission to share it with you.","actions":[{"name":"Comment","link":"https://www.facebook.com/172338516139198/posts/829026050470438"},{"name":"Like","link":"https://www.facebook.com/172338516139198/posts/829026050470438"}],"privacy":{"value":""},"type":"status","created_time":"2014-10-12T05:16:15+0000","updated_time":"2014-10-12T05:16:15+0000","likes":{"data":[{"id":"755026046","name":"Mosab Ahmad"},{"id":"100001380771403","name":"Ahmed Elnady"},{"id":"695596001","name":"Muhammad Saleh"}],"paging":{"cursors":{"after":"Njk1NTk2MDAx","before":"NzU1MDI2MDQ2"}}}}