{"id":"172338516139198_914782081894834","from":{"name":"Hisham Abd El-Hafez Eid","id":"10155080508766171"},"message":"NASA Space Apps are looking for mentors who would coach Hackathon teams through the competition. All senior geeks are welcomed to volunteer and specially entrepreneurs. Read all about it below\n\n#I_am_not_a_job_ad","story":"Hisham Abd El-Hafez Eid shared NASA Space Apps Cairo's photo to the group: Egyptian Geeks.","story_tags":{"0":[{"id":"10155080508766171","name":"Hisham Abd El-Hafez Eid","type":"user","offset":0,"length":23}],"31":[{"id":"648424618616505","name":"NASA Space Apps Cairo","type":"page","offset":31,"length":21}],"55":[{"id":"680920728700227","name":"","offset":55,"length":5}],"75":[{"id":"172338516139198","name":"Egyptian Geeks","type":"group","offset":75,"length":14}]},"picture":"https://fb-s-b-a.akamaihd.net/h-ak-xfa1/v/t1.0-0/s130x130/11010307_680920728700227_1136575475886519862_n.jpg?oh=3180ac6e7a31f189886a8cfebe2532b8&oe=5970F0F9&__gda__=1496035857_0ac0d02dec8a2fe02a06c34428651eb3","link":"https://www.facebook.com/spaceappscairo/photos/a.674651615993805.1073741828.648424618616505/680920728700227/?type=3","name":"NASA Space Apps Cairo","description":"The Space Apps Challenge Hackathon wouldn't be complete without passionate mentors sharing their insights on how to find solutions in the 4 categories; Robotics, Outer Space, Humans and Earth.\n\nIf you have the spirit, time and energy for a 48-hour hackathon, and ready to share your valuable expertise in solving the Space Apps Challenges, you're more than welcome to join us!\n\nJoin us now here > http://spaceappscairo.com/mentors.html\n\nRead more on the challenges > http://goo.gl/hGyA8F\n\n#SpaceAppsCairo\n#SpaceApps","actions":[{"name":"Comment","link":"https://www.facebook.com/172338516139198/posts/914782081894834"},{"name":"Like","link":"https://www.facebook.com/172338516139198/posts/914782081894834"},{"name":"Report Post to Admin","link":"https://www.facebook.com/groups/egyptian.geeks/members/"}],"privacy":{"value":"","description":"","friends":"","allow":"","deny":""},"type":"photo","object_id":"680920728700227","created_time":"2015-03-25T15:33:13+0000","updated_time":"2015-03-25T16:48:01+0000","is_hidden":false,"is_expired":false,"likes":{"data":[{"id":"10154215525191922","name":"Ahmed Sadek Mohamed Tawfik"}],"paging":{"cursors":{"before":"MTAxNTQyMTU1MjUxOTE5MjIZD","after":"MTAxNTQyMTU1MjUxOTE5MjIZD"}}},"comments":{"data":[{"created_time":"2015-03-25T16:48:01+0000","from":{"name":"Ahmed Sadek Mohamed Tawfik","id":"10154215525191922"},"message":"shakloh gamed el 7ewar dah :D .. I am in :D","can_remove":false,"like_count":0,"user_likes":false,"id":"914813735225002"}],"paging":{"cursors":{"before":"WTI5dGJXVnVkRjlqZAFhKemIzSTZAPVEUwT0RFek56TTFNakkxTURBeU9qRTBNamN6TURJd09ERT0ZD","after":"WTI5dGJXVnVkRjlqZAFhKemIzSTZAPVEUwT0RFek56TTFNakkxTURBeU9qRTBNamN6TURJd09ERT0ZD"}}}}