{"id":"172338516139198_561884327184613","from":{"id":"740765313","name":"Mohamed Elsherif"},"to":{"data":[{"name":"Egyptian Geeks","id":"172338516139198"}]},"message":"اللقاء الأسبوعي العاشر لمجموعة اسأل مطور, في هذا الأسبوع نناقش البرمجة بJavascript و نتطرق لموضوع node.js \nالأجندة.\nIntroduction and History for Javascript\nThe love & hate relationship between developers & javascript\nJavascript on the client\nGoogle Chrome V8 engine\nNode.js \nAsynchronous IO benefits","picture":"https://fbexternal-a.akamaihd.net/safe_image.php?d=AQDvd8rGv40gm4NK&w=130&h=130&url=http%3A%2F%2Fi4.ytimg.com%2Fvi%2F_hZEMpNE6QE%2Fhqdefault.jpg%3Ffeature%3Dog","link":"http://www.youtube.com/watch?v=_hZEMpNE6QE","source":"http://www.youtube.com/v/_hZEMpNE6QE?autohide=1&version=3&autoplay=1","name":"Ask Developer Hangout - 10 - Javascript & Node.js","icon":"https://fbstatic-a.akamaihd.net/rsrc.php/v2/yj/r/v2OnaTyTQZE.gif","actions":[{"name":"Comment","link":"https://www.facebook.com/172338516139198/posts/561884327184613"},{"name":"Like","link":"https://www.facebook.com/172338516139198/posts/561884327184613"}],"privacy":{"value":""},"type":"video","created_time":"2013-05-05T04:16:34+0000","updated_time":"2013-05-05T04:22:39+0000","likes":{"data":[{"id":"1614120164","name":"Eslam Hamouda"},{"id":"100003095968023","name":"Ashraf Hesham"}],"paging":{"cursors":{"after":"MTAwMDAzMDk1OTY4MDIz","before":"MTYxNDEyMDE2NA=="}}},"comments":{"data":[{"id":"561884690517910","from":{"id":"100000126429020","name":"Ahmed Mahmoud"},"message":"Ashraf Hesham chcek :D","message_tags":[{"id":"100003095968023","name":"Ashraf Hesham","type":"user","offset":0,"length":13}],"can_remove":false,"created_time":"2013-05-05T04:18:36+0000","like_count":1,"user_likes":false},{"id":"561885763851136","from":{"id":"100003095968023","name":"Ashraf Hesham"},"message":"GREAT","can_remove":false,"created_time":"2013-05-05T04:22:39+0000","like_count":0,"user_likes":false}],"paging":{"cursors":{"after":"NTYxODg1NzYzODUxMTM2","before":"NTYxODg0NjkwNTE3OTEw"}}}}