{"id":"172338516139198_728930090480035","from":{"id":"661261340","name":"Mohammad Tayseer"},"to":{"data":[{"name":"Egyptian Geeks","id":"172338516139198"}]},"picture":"https://fbexternal-a.akamaihd.net/safe_image.php?d=AQAmoBeppDH6HlDo&w=154&h=154&url=http%3A%2F%2Fwww.redditstatic.com%2Fkill.png","link":"http://www.reddit.com/r/MachineLearning/comments/22q2q4/biweekly_classification_challenge_1_car_detection/","name":"[Bi-Weekly Classification Challenge #1] Car Detection : MachineLearning","caption":"www.reddit.com","description":"**INTRO** http://www.reddit.com/r/MachineLearning/comments/22ohrb/meta_how_about_weekly_contests_in_classification/ Many people expressed their int...","icon":"https://fbstatic-a.akamaihd.net/rsrc.php/v2/yD/r/aS8ecmYRys0.gif","actions":[{"name":"Comment","link":"https://www.facebook.com/172338516139198/posts/728930090480035"},{"name":"Like","link":"https://www.facebook.com/172338516139198/posts/728930090480035"}],"privacy":{"value":""},"type":"link","created_time":"2014-04-11T19:34:58+0000","updated_time":"2014-04-11T19:34:58+0000","likes":{"data":[{"id":"568795330","name":"Ahmed Attyah"}],"paging":{"cursors":{"after":"NTY4Nzk1MzMw","before":"NTY4Nzk1MzMw"}}}}