{"id":"172338516139198_780981215274922","from":{"id":"660220583","name":"Adel K. Khalil"},"to":{"data":[{"name":"Egyptian Geeks","id":"172338516139198"}]},"picture":"https://fbexternal-a.akamaihd.net/safe_image.php?d=AQCfv5MtMGLW0CzT&w=130&h=130&url=http%3A%2F%2Fi1.ytimg.com%2Fvi%2FfpbOEoRrHyU%2Fmaxresdefault.jpg","link":"https://www.youtube.com/watch?v=fpbOEoRrHyU","source":"http://www.youtube.com/v/fpbOEoRrHyU?autohide=1&version=3&autoplay=1","name":"Last Week Tonight with John Oliver: Net Neutrality (HBO)","description":"Cable companies are trying to create an unequal playing field for internet speeds, but they're doing it so boringly that most news outlets aren't covering it...","icon":"https://fbstatic-a.akamaihd.net/rsrc.php/v2/yj/r/v2OnaTyTQZE.gif","actions":[{"name":"Comment","link":"https://www.facebook.com/172338516139198/posts/780981215274922"},{"name":"Like","link":"https://www.facebook.com/172338516139198/posts/780981215274922"}],"privacy":{"value":""},"type":"video","created_time":"2014-07-10T19:34:44+0000","updated_time":"2014-07-10T19:34:44+0000"}