{"posts":[{"id":"172338516139198_554161037956942","from":{"name":"Mohamed Elsherif","id":"10158483817400314"},"message":"مقطع من لقاء السبت الماضي يناقش بموضوعية قضية التابلت المصري إينار","caption":"youtube.com","description":"ده مقطع من اللقاء الاسبوعي لمجموعة المطورين المصريين, في الأسبوع ده ناقشنا موضوع المصادر المفتوحة و الفوائد و المميزات في الطريقة دي في التطوير و تطرقنا الى ...","created_time":"2013-04-15T17:21:53+10:00","total_likes":3,"total_comments":2},{"id":"172338516139198_554614644578248","from":{"name":"Mohammad Tayseer","id":"10154965677956341"},"message":null,"caption":"udacity.com","description":"Learn about cryptography and how encryption and key exchange have a role in computer security.  This class is free, start learning!","created_time":"2013-04-17T01:14:34+10:00","total_likes":1,"total_comments":0},{"id":"172338516139198_554614651244914","from":{"name":"Kareem Elansary","id":"10155149930945530"},"message":"any help here to install Meteor on windows ?","caption":null,"description":null,"created_time":"2013-04-17T01:14:35+10:00","total_likes":0,"total_comments":2},{"id":"172338516139198_554760444563668","from":{"name":"Mohamed Alaa El Din","id":"1252478278163674"},"message":null,"caption":"vimeo.com","description":"A talk I delivered about front end performance in March 2013 to Stockholm JS. The event was hosted by Spotify.","created_time":"2013-04-17T10:00:22+10:00","total_likes":0,"total_comments":0},{"id":"172338516139198_554562164583496","from":{"name":"Mahmoud Ibrahim","id":"10154874374735831"},"message":null,"caption":"ted.com","description":"What motivates us to work? Contrary to conventional wisdom, it isn't just money. But it's not exactly joy either. It seems that most of us thrive by making constant progress and feeling a sense of purpose. Behavioral economist Dan Ariely presents two eye-opening experiments that reveal our unexpecte...","created_time":"2013-04-16T21:51:23+10:00","total_likes":1,"total_comments":1},{"id":"172338516139198_554760951230284","from":{"name":"Mohamed Alaa El Din","id":"1252478278163674"},"message":"Windows XP :D Kafa2at 3alyah :D","caption":"youtube.com","description":"من داخل مصنع بنها للصناعات وأول لوحي مصري","created_time":"2013-04-17T10:02:47+10:00","total_likes":0,"total_comments":8},{"id":"172338516139198_554973504542362","from":{"name":"Mohamed Sameeh Sharaf","id":"1704851202862067"},"message":"I am very pleased to announce the general availability of Windows Azure Infrastructure Services. This new service now makes it possible for customers to move applications into the cloud.\n:)","caption":"blogs.msdn.com","description":"Today is an exciting day for Microsoft, Windows Azure and all of our customers around the world.  I am very pleased to announce the general availability of Windows Azure Infrastructure Services. This new service now makes it possible for customers to move applications into the cloud.","created_time":"2013-04-18T01:59:19+10:00","total_likes":0,"total_comments":0},{"id":"172338516139198_555023084537404","from":{"name":"Mohamed Alaa El Din","id":"1252478278163674"},"message":null,"caption":"topcoat.io","description":null,"created_time":"2013-04-18T04:13:06+10:00","total_likes":0,"total_comments":0},{"id":"172338516139198_555024981203881","from":{"name":"Mohamed Alaa El Din","id":"1252478278163674"},"message":"http://www.instantshift.com/2013/04/15/80-amazing-vector-art-for-designers/?utm_source=feedly&utm_medium=feed&utm_campaign=Feed%3A+iShift+%28instantShift%29","caption":"instantshift.com","description":"If you've ever worked with design, you know the necessity of having a good set of vector images downloaded on your computer. Vector art can indeed come in handy when working on different types of design projects. Their main advantage is, obviously, that t","created_time":"2013-04-18T04:20:38+10:00","total_likes":0,"total_comments":0},{"id":"172338516139198_555026514537061","from":{"name":"Mohamed Alaa El Din","id":"1252478278163674"},"message":null,"caption":"hongkiat.com","description":"There are two types of transform available in CSS3 specification, 2D and 3D. In our previous post, we have discussed on CSS3 Transform 2D. So, this time, we are going to look into transform elements in 3D space and specifically in this post, we are going to also create the ... Continue reading »","created_time":"2013-04-18T04:25:53+10:00","total_likes":0,"total_comments":0}]}