{"posts":[{"id":"172338516139198_727516090621435","from":{"id":"1486650909","name":"Khaled M. Diab"},"message":"Heartbleed bug is a serious bug in OpenSSL that affects many web services/servers/apps ..","caption":"heartbleed.com","description":"The Heartbleed Bug is a serious vulnerability in the popular OpenSSL cryptographic software library. This weakness allows stealing the information protected, under normal conditions, by the SSL/TLS encryption used to secure the Internet. SSL/TLS provides communication security and privacy over the I...","created_time":"2014-04-09T09:13:18+03:00","total_likes":3,"total_comments":8},{"id":"172338516139198_728930090480035","from":{"id":"661261340","name":"Mohammad Tayseer"},"message":null,"caption":"www.reddit.com","description":"**INTRO** http://www.reddit.com/r/MachineLearning/comments/22ohrb/meta_how_about_weekly_contests_in_classification/ Many people expressed their int...","created_time":"2014-04-11T22:34:58+03:00","total_likes":1,"total_comments":0},{"id":"172338516139198_728548540518190","from":{"id":"544815169","name":"Mohamed Meligy"},"message":"React Conf Videos\n\nMore info about the conference: http://reactconf.com/\n \nThey will upload the videos here: https://www.youtube.com/user/reactconf/videos (there are a few already)","caption":"www.youtube.com","description":null,"created_time":"2014-04-11T04:20:30+03:00","total_likes":1,"total_comments":1},{"id":"172338516139198_729033423803035","from":{"id":"661261340","name":"Mohammad Tayseer"},"message":"Work in MIT","caption":"scratch.mit.edu","description":"Want to work on an innovative project that is transforming the ways young people create, share, and learn? Join the Scratch Team!","created_time":"2014-04-12T02:04:01+03:00","total_likes":0,"total_comments":0},{"id":"172338516139198_729061227133588","from":{"id":"540788204","name":"Ahmed Hassan"},"message":"In remembrance of XP....","caption":"In remembrance of XP (y)","description":"#Technob0y","created_time":"2014-04-12T03:31:15+03:00","total_likes":1,"total_comments":0},{"id":"172338516139198_729185633787814","from":{"id":"100002045429029","name":"مُحَمَّد أبو آدم"},"message":"http://blogs.msdn.com/b/oldnewthing/archive/2014/04/11/10516280.aspx","caption":null,"description":null,"created_time":"2014-04-12T08:26:46+03:00","total_likes":0,"total_comments":0},{"id":"172338516139198_729222113784166","from":{"id":"665359179","name":"Ahmed T. Al-Amir"},"message":"A security breach on Google's own servers.","caption":"Attachment UnavailableThis attachment may have been removed or the person who shared it may not have permission to share it with you.","description":null,"created_time":"2014-04-12T11:00:21+03:00","total_likes":1,"total_comments":1},{"id":"172338516139198_729334473772930","from":{"id":"100000146926215","name":"BęĎő Moez"},"message":"Egyptian python programmers are required, contact if you are interested.\nContact mail: abdelrahman.moez@gmail.com","caption":null,"description":null,"created_time":"2014-04-12T15:17:03+03:00","total_likes":0,"total_comments":0},{"id":"172338516139198_729465007093210","from":{"id":"740765313","name":"Mohamed Elsherif"},"message":"رابط الهانجاوت, انضم لنا الآن على الهواء\nhttps://plus.google.com/hangouts/_/hoaevent/AP36tYcNWTOjg9kcpri8LFuB1Bn1WAzfbM5Rf9ZGwDj0rP4j_7ZikA?authuser=0&hl=en\n\nرابط اليوتيوب لو مش لاقي مكان \nhttp://youtu.be/eePN0j_V2Pw","caption":null,"description":"رابط الهانجاوت, انضم لنا الآن على الهواء\nhttps://plus.google.com/hangouts/_/hoaevent/AP36tYcNWTOjg9kcpri8LFuB1Bn1WAzfbM5Rf9ZGwDj0rP4j_7ZikA?authuser=0&hl=en\n\nرابط اليوتيوب لو مش لاقي مكان \nhttp://youtu.be/eePN0j_V2Pw","created_time":"2014-04-12T21:02:07+03:00","total_likes":1,"total_comments":0},{"id":"172338516139198_729468110426233","from":{"id":"100002045429029","name":"مُحَمَّد أبو آدم"},"message":null,"caption":"Attachment UnavailableThis attachment may have been removed or the person who shared it may not have permission to share it with you.","description":null,"created_time":"2014-04-12T21:11:34+03:00","total_likes":0,"total_comments":0}]}